{
    "Bones": {
        "CC_Base_R_Hand": 1.0,
        "CC_Base_R_Ring1": 1.0,
        "CC_Base_R_Ring2": 1.0,
        "CC_Base_R_Ring3": 1.0,
        "CC_Base_R_Mid1": 1.0,
        "CC_Base_R_Mid2": 1.0,
        "CC_Base_R_Mid3": 1.0,
        "CC_Base_R_Thumb1": 1.0,
        "CC_Base_R_Thumb2": 1.0,
        "CC_Base_R_Thumb3": 1.0,
        "CC_Base_R_Index1": 1.0,
        "CC_Base_R_Index2": 1.0,
        "CC_Base_R_Index3": 1.0,
        "CC_Base_R_Pinky1": 1.0,
        "CC_Base_R_Pinky2": 1.0,
        "CC_Base_R_Pinky3": 1.0,
        "hand_tweak.R": 1.0,
        "hand_fk.R": 1.0,
        "f_index.01_master.R": 1.0,
        "thumb.01_master.R": 1.0,
        "f_index.01.R": 1.0,
        "f_index.02.R": 1.0,
        "f_index.03.R": 1.0,
        "f_index.01.R.001": 1.0,
        "thumb.01.R": 1.0,
        "thumb.02.R": 1.0,
        "thumb.03.R": 1.0,
        "thumb.01.R.001": 1.0,
        "f_middle.01_master.R": 1.0,
        "f_middle.01.R": 1.0,
        "f_middle.02.R": 1.0,
        "f_middle.03.R": 1.0,
        "f_middle.01.R.001": 1.0,
        "f_ring.01_master.R": 1.0,
        "f_ring.01.R": 1.0,
        "f_ring.02.R": 1.0,
        "f_ring.03.R": 1.0,
        "f_ring.01.R.001": 1.0,
        "f_pinky.01_master.R": 1.0,
        "f_pinky.01.R": 1.0,
        "f_pinky.02.R": 1.0,
        "f_pinky.03.R": 1.0,
        "f_pinky.01.R.001": 1.0,
        "palm.R": 1.0,
        "hand_ik.R": 1.0,
        "upper_arm_ik_target.R": 1.0,
        "hand_r": 1.0,
        "middle_01_r": 1.0,
        "middle_02_r": 1.0,
        "middle_03_r": 1.0,
        "ring_01_r": 1.0,
        "ring_02_r": 1.0,
        "ring_03_r": 1.0,
        "thumb_01_r": 1.0,
        "thumb_02_r": 1.0,
        "thumb_03_r": 1.0,
        "index_01_r": 1.0,
        "index_02_r": 1.0,
        "index_03_r": 1.0,
        "pinky_01_r": 1.0,
        "pinky_02_r": 1.0,
        "pinky_03_r": 1.0
    },
    "Keys": {}
}